{
  "generated_at": "2026-02-01T12:07:25.319617",
  "version": "1.0",
  "data": {
    "report_generated": "2026-02-01T12:07:25.319602",
    "scan_summary": {
      "total_folders_found": 5,
      "total_files_found": 19
    },
    "processing_summary": {
      "total_folders_processed": 5,
      "total_files_processed": 19,
      "total_errors": 0,
      "total_skipped": 0,
      "success_rate": 100.0
    },
    "detailed_results": [
      {
        "folder_guid": "801aa850-79c4-4eba-8c65-dd74d8ac9b33",
        "folder_path": "C:\\_sample\\tree_test\\20300123456\\source\\smith",
        "folder_name": "smith",
        "total_files": 3,
        "processed_files": 3,
        "error_files": 0,
        "skipped_files": 0,
        "file_results": [
          {
            "file_guid": "5ef04505-4649-4714-b3e2-254c9a1f9d2d",
            "filename": "document (2).pdf",
            "filepath": "C:\\_sample\\tree_test\\20300123456\\source\\smith\\document (2).pdf",
            "folder_guid": "801aa850-79c4-4eba-8c65-dd74d8ac9b33",
            "status": "completed",
            "file_type": "pdf",
            "file_size": 420098,
            "processed_at": "2026-02-01T12:07:25.315461",
            "error_message": null,
            "metadata": {
              "extracted_at": "2026-02-01T12:07:25.315362",
              "created": "2026-01-17T22:35:51.725887",
              "modified": "2025-10-11T23:57:57.614534",
              "accessed": "2026-01-18T15:58:30.300420",
              "page_count": null,
              "pdf_version": null
            }
          },
          {
            "file_guid": "9d6c340d-69d9-4b1f-b013-ab20d0b7801d",
            "filename": "dummy_statement.pdf",
            "filepath": "C:\\_sample\\tree_test\\20300123456\\source\\smith\\dummy_statement.pdf",
            "folder_guid": "801aa850-79c4-4eba-8c65-dd74d8ac9b33",
            "status": "completed",
            "file_type": "pdf",
            "file_size": 183623,
            "processed_at": "2026-02-01T12:07:25.315686",
            "error_message": null,
            "metadata": {
              "extracted_at": "2026-02-01T12:07:25.315609",
              "created": "2026-01-17T22:35:51.734761",
              "modified": "2025-10-11T23:57:32.221820",
              "accessed": "2026-01-18T15:58:30.328377",
              "page_count": null,
              "pdf_version": null
            }
          },
          {
            "file_guid": "3035cb94-b0f0-4aa6-a4c6-8149013f90da",
            "filename": "tiaa PDF_Participant-statement-sample2.pdf",
            "filepath": "C:\\_sample\\tree_test\\20300123456\\source\\smith\\tiaa PDF_Participant-statement-sample2.pdf",
            "folder_guid": "801aa850-79c4-4eba-8c65-dd74d8ac9b33",
            "status": "completed",
            "file_type": "pdf",
            "file_size": 1014752,
            "processed_at": "2026-02-01T12:07:25.315908",
            "error_message": null,
            "metadata": {
              "extracted_at": "2026-02-01T12:07:25.315834",
              "created": "2026-01-17T22:35:51.744761",
              "modified": "2025-09-23T07:47:53.372530",
              "accessed": "2026-01-18T15:58:30.350376",
              "page_count": null,
              "pdf_version": null
            }
          }
        ],
        "started_at": "2026-02-01T12:07:25.315918",
        "completed_at": "2026-02-01T12:07:25.315912"
      },
      {
        "folder_guid": "87d8ddca-f89f-41eb-ab59-143996c5b297",
        "folder_path": "C:\\_sample\\tree_test\\20300123457\\pdfs\\54321",
        "folder_name": "54321",
        "total_files": 4,
        "processed_files": 4,
        "error_files": 0,
        "skipped_files": 0,
        "file_results": [
          {
            "file_guid": "a80a5019-426b-49b2-8c79-fb9ec9f85edb",
            "filename": "08_LP1_Financial-Document-Samples_01.28.19.pdf",
            "filepath": "C:\\_sample\\tree_test\\20300123457\\pdfs\\54321\\08_LP1_Financial-Document-Samples_01.28.19.pdf",
            "folder_guid": "87d8ddca-f89f-41eb-ab59-143996c5b297",
            "status": "completed",
            "file_type": "pdf",
            "file_size": 265266,
            "processed_at": "2026-02-01T12:07:25.316233",
            "error_message": null,
            "metadata": {
              "extracted_at": "2026-02-01T12:07:25.316161",
              "created": "2026-01-17T22:43:24.783922",
              "modified": "2025-10-12T00:00:00.689257",
              "accessed": "2026-01-18T15:58:30.413376",
              "page_count": null,
              "pdf_version": null
            }
          },
          {
            "file_guid": "cc822d20-b811-45c3-a77b-15b49047154f",
            "filename": "Commerce_statement_sample1.pdf",
            "filepath": "C:\\_sample\\tree_test\\20300123457\\pdfs\\54321\\Commerce_statement_sample1.pdf",
            "folder_guid": "87d8ddca-f89f-41eb-ab59-143996c5b297",
            "status": "completed",
            "file_type": "pdf",
            "file_size": 55071,
            "processed_at": "2026-02-01T12:07:25.316425",
            "error_message": null,
            "metadata": {
              "extracted_at": "2026-02-01T12:07:25.316355",
              "created": "2026-01-17T22:43:24.796702",
              "modified": "2025-10-11T23:58:26.644558",
              "accessed": "2026-01-18T15:58:30.433406",
              "page_count": null,
              "pdf_version": null
            }
          },
          {
            "file_guid": "c3648cc7-9f12-41cf-9cbf-03f2686cb465",
            "filename": "document (2).pdf",
            "filepath": "C:\\_sample\\tree_test\\20300123457\\pdfs\\54321\\document (2).pdf",
            "folder_guid": "87d8ddca-f89f-41eb-ab59-143996c5b297",
            "status": "completed",
            "file_type": "pdf",
            "file_size": 420098,
            "processed_at": "2026-02-01T12:07:25.316611",
            "error_message": null,
            "metadata": {
              "extracted_at": "2026-02-01T12:07:25.316544",
              "created": "2026-01-17T22:43:24.807287",
              "modified": "2025-10-11T23:57:57.614534",
              "accessed": "2026-01-18T15:58:30.453376",
              "page_count": null,
              "pdf_version": null
            }
          },
          {
            "file_guid": "3320c6db-71e3-48f0-bc82-a283034deda9",
            "filename": "dummy_statement.pdf",
            "filepath": "C:\\_sample\\tree_test\\20300123457\\pdfs\\54321\\dummy_statement.pdf",
            "folder_guid": "87d8ddca-f89f-41eb-ab59-143996c5b297",
            "status": "completed",
            "file_type": "pdf",
            "file_size": 183623,
            "processed_at": "2026-02-01T12:07:25.316811",
            "error_message": null,
            "metadata": {
              "extracted_at": "2026-02-01T12:07:25.316742",
              "created": "2026-01-17T22:43:24.824286",
              "modified": "2025-10-11T23:57:32.221820",
              "accessed": "2026-01-18T15:58:30.474419",
              "page_count": null,
              "pdf_version": null
            }
          }
        ],
        "started_at": "2026-02-01T12:07:25.316820",
        "completed_at": "2026-02-01T12:07:25.316815"
      },
      {
        "folder_guid": "5a86e55a-7666-4e35-8fb3-2b78b4f6aae9",
        "folder_path": "C:\\_sample\\tree_test\\20300123457\\pdfs\\jones",
        "folder_name": "jones",
        "total_files": 4,
        "processed_files": 4,
        "error_files": 0,
        "skipped_files": 0,
        "file_results": [
          {
            "file_guid": "a5299c0c-b78b-4684-aae5-40375c6e6c2d",
            "filename": "08_LP1_Financial-Document-Samples_01.28.19.pdf",
            "filepath": "C:\\_sample\\tree_test\\20300123457\\pdfs\\jones\\08_LP1_Financial-Document-Samples_01.28.19.pdf",
            "folder_guid": "5a86e55a-7666-4e35-8fb3-2b78b4f6aae9",
            "status": "completed",
            "file_type": "pdf",
            "file_size": 265266,
            "processed_at": "2026-02-01T12:07:25.317155",
            "error_message": null,
            "metadata": {
              "extracted_at": "2026-02-01T12:07:25.317083",
              "created": "2026-01-17T22:36:51.810550",
              "modified": "2025-10-12T00:00:00.689257",
              "accessed": "2026-01-18T15:58:30.511378",
              "page_count": null,
              "pdf_version": null
            }
          },
          {
            "file_guid": "703fbab1-36f0-4835-a12c-fb594dcafe6c",
            "filename": "Commerce_statement_sample1.pdf",
            "filepath": "C:\\_sample\\tree_test\\20300123457\\pdfs\\jones\\Commerce_statement_sample1.pdf",
            "folder_guid": "5a86e55a-7666-4e35-8fb3-2b78b4f6aae9",
            "status": "completed",
            "file_type": "pdf",
            "file_size": 55071,
            "processed_at": "2026-02-01T12:07:25.317349",
            "error_message": null,
            "metadata": {
              "extracted_at": "2026-02-01T12:07:25.317280",
              "created": "2026-01-17T22:36:51.822558",
              "modified": "2025-10-11T23:58:26.644558",
              "accessed": "2026-01-18T15:58:30.535378",
              "page_count": null,
              "pdf_version": null
            }
          },
          {
            "file_guid": "328d37af-8edc-4a06-a026-8cdafed5e502",
            "filename": "document (2).pdf",
            "filepath": "C:\\_sample\\tree_test\\20300123457\\pdfs\\jones\\document (2).pdf",
            "folder_guid": "5a86e55a-7666-4e35-8fb3-2b78b4f6aae9",
            "status": "completed",
            "file_type": "pdf",
            "file_size": 420098,
            "processed_at": "2026-02-01T12:07:25.317534",
            "error_message": null,
            "metadata": {
              "extracted_at": "2026-02-01T12:07:25.317468",
              "created": "2026-01-17T22:36:51.838708",
              "modified": "2025-10-11T23:57:57.614534",
              "accessed": "2026-01-18T15:58:30.558376",
              "page_count": null,
              "pdf_version": null
            }
          },
          {
            "file_guid": "e89ceaa4-f1d9-413a-bae7-46ce4f0d4bc9",
            "filename": "dummy_statement.pdf",
            "filepath": "C:\\_sample\\tree_test\\20300123457\\pdfs\\jones\\dummy_statement.pdf",
            "folder_guid": "5a86e55a-7666-4e35-8fb3-2b78b4f6aae9",
            "status": "completed",
            "file_type": "pdf",
            "file_size": 183623,
            "processed_at": "2026-02-01T12:07:25.317717",
            "error_message": null,
            "metadata": {
              "extracted_at": "2026-02-01T12:07:25.317651",
              "created": "2026-01-17T22:36:51.796558",
              "modified": "2025-10-11T23:57:32.221820",
              "accessed": "2026-01-18T15:58:30.579378",
              "page_count": null,
              "pdf_version": null
            }
          }
        ],
        "started_at": "2026-02-01T12:07:25.317724",
        "completed_at": "2026-02-01T12:07:25.317720"
      },
      {
        "folder_guid": "49db09ef-41cb-45c8-a628-6d3d1673eb19",
        "folder_path": "C:\\_sample\\tree_test\\20300123458\\app_files\\pdfs\\baker",
        "folder_name": "baker",
        "total_files": 4,
        "processed_files": 4,
        "error_files": 0,
        "skipped_files": 0,
        "file_results": [
          {
            "file_guid": "1b15b486-e806-437c-a258-562618f2baa1",
            "filename": "2025_05_16_1035-form-Handwriting-sample-003-compressed-01.pdf",
            "filepath": "C:\\_sample\\tree_test\\20300123458\\app_files\\pdfs\\baker\\2025_05_16_1035-form-Handwriting-sample-003-compressed-01.pdf",
            "folder_guid": "49db09ef-41cb-45c8-a628-6d3d1673eb19",
            "status": "completed",
            "file_type": "pdf",
            "file_size": 992732,
            "processed_at": "2026-02-01T12:07:25.318015",
            "error_message": null,
            "metadata": {
              "extracted_at": "2026-02-01T12:07:25.317945",
              "created": "2026-01-17T22:37:27.761978",
              "modified": "2025-05-16T20:38:14.379310",
              "accessed": "2026-01-17T22:37:27.765145",
              "page_count": null,
              "pdf_version": null
            }
          },
          {
            "file_guid": "28ef26d6-ff6b-4d2c-8485-5bfc85446143",
            "filename": "2025_05_16_1035-form-Handwriting-sample-003-copy.pdf",
            "filepath": "C:\\_sample\\tree_test\\20300123458\\app_files\\pdfs\\baker\\2025_05_16_1035-form-Handwriting-sample-003-copy.pdf",
            "folder_guid": "49db09ef-41cb-45c8-a628-6d3d1673eb19",
            "status": "completed",
            "file_type": "pdf",
            "file_size": 10025131,
            "processed_at": "2026-02-01T12:07:25.318209",
            "error_message": null,
            "metadata": {
              "extracted_at": "2026-02-01T12:07:25.318141",
              "created": "2026-01-17T22:37:27.773904",
              "modified": "2025-05-16T20:32:51.560553",
              "accessed": "2026-01-17T22:37:27.778973",
              "page_count": null,
              "pdf_version": null
            }
          },
          {
            "file_guid": "94cfa79f-609a-4c0e-997d-4e20b4c28f8a",
            "filename": "2025_05_16_1035-form-Handwriting-sample-003-IMAGE-Only.pdf",
            "filepath": "C:\\_sample\\tree_test\\20300123458\\app_files\\pdfs\\baker\\2025_05_16_1035-form-Handwriting-sample-003-IMAGE-Only.pdf",
            "folder_guid": "49db09ef-41cb-45c8-a628-6d3d1673eb19",
            "status": "completed",
            "file_type": "pdf",
            "file_size": 8441953,
            "processed_at": "2026-02-01T12:07:25.318412",
            "error_message": null,
            "metadata": {
              "extracted_at": "2026-02-01T12:07:25.318341",
              "created": "2026-01-17T22:37:27.735983",
              "modified": "2025-05-18T09:48:47.886810",
              "accessed": "2026-01-17T22:37:27.739964",
              "page_count": null,
              "pdf_version": null
            }
          },
          {
            "file_guid": "f1960971-3679-4366-ba84-7910efb5b15b",
            "filename": "2025_05_16_1035-form-Handwriting-sample-003.pdf",
            "filepath": "C:\\_sample\\tree_test\\20300123458\\app_files\\pdfs\\baker\\2025_05_16_1035-form-Handwriting-sample-003.pdf",
            "folder_guid": "49db09ef-41cb-45c8-a628-6d3d1673eb19",
            "status": "completed",
            "file_type": "pdf",
            "file_size": 10019982,
            "processed_at": "2026-02-01T12:07:25.318601",
            "error_message": null,
            "metadata": {
              "extracted_at": "2026-02-01T12:07:25.318533",
              "created": "2026-01-17T22:37:27.748020",
              "modified": "2025-05-16T18:47:25",
              "accessed": "2026-01-17T22:37:27.752976",
              "page_count": null,
              "pdf_version": null
            }
          }
        ],
        "started_at": "2026-02-01T12:07:25.318607",
        "completed_at": "2026-02-01T12:07:25.318604"
      },
      {
        "folder_guid": "7a241453-7256-4c69-861b-dc6427644bde",
        "folder_path": "C:\\_sample\\tree_test\\20300123458\\app_files\\pdfs\\client02",
        "folder_name": "client02",
        "total_files": 4,
        "processed_files": 4,
        "error_files": 0,
        "skipped_files": 0,
        "file_results": [
          {
            "file_guid": "59fce7c7-7168-4670-ae42-be3fd79ab4c6",
            "filename": "08_LP1_Financial-Document-Samples_01.28.19.pdf",
            "filepath": "C:\\_sample\\tree_test\\20300123458\\app_files\\pdfs\\client02\\08_LP1_Financial-Document-Samples_01.28.19.pdf",
            "folder_guid": "7a241453-7256-4c69-861b-dc6427644bde",
            "status": "completed",
            "file_type": "pdf",
            "file_size": 265266,
            "processed_at": "2026-02-01T12:07:25.318907",
            "error_message": null,
            "metadata": {
              "extracted_at": "2026-02-01T12:07:25.318837",
              "created": "2026-01-17T22:48:59.115196",
              "modified": "2025-10-12T00:00:00.689257",
              "accessed": "2026-01-18T15:58:30.780379",
              "page_count": null,
              "pdf_version": null
            }
          },
          {
            "file_guid": "a7b0f811-4974-404e-9110-01b3a9b51224",
            "filename": "Commerce_statement_sample1.pdf",
            "filepath": "C:\\_sample\\tree_test\\20300123458\\app_files\\pdfs\\client02\\Commerce_statement_sample1.pdf",
            "folder_guid": "7a241453-7256-4c69-861b-dc6427644bde",
            "status": "completed",
            "file_type": "pdf",
            "file_size": 55071,
            "processed_at": "2026-02-01T12:07:25.319093",
            "error_message": null,
            "metadata": {
              "extracted_at": "2026-02-01T12:07:25.319025",
              "created": "2026-01-17T22:48:59.123244",
              "modified": "2025-10-11T23:58:26.644558",
              "accessed": "2026-01-18T15:58:30.809380",
              "page_count": null,
              "pdf_version": null
            }
          },
          {
            "file_guid": "520ba726-b803-4349-b63b-69a66cfa5c0a",
            "filename": "document (2).pdf",
            "filepath": "C:\\_sample\\tree_test\\20300123458\\app_files\\pdfs\\client02\\document (2).pdf",
            "folder_guid": "7a241453-7256-4c69-861b-dc6427644bde",
            "status": "completed",
            "file_type": "pdf",
            "file_size": 420098,
            "processed_at": "2026-02-01T12:07:25.319306",
            "error_message": null,
            "metadata": {
              "extracted_at": "2026-02-01T12:07:25.319238",
              "created": "2026-01-17T22:48:59.131235",
              "modified": "2025-10-11T23:57:57.614534",
              "accessed": "2026-01-18T15:58:30.839377",
              "page_count": null,
              "pdf_version": null
            }
          },
          {
            "file_guid": "5230d4d4-c8ab-4de9-89a5-24418c63a192",
            "filename": "dummy_statement.pdf",
            "filepath": "C:\\_sample\\tree_test\\20300123458\\app_files\\pdfs\\client02\\dummy_statement.pdf",
            "folder_guid": "7a241453-7256-4c69-861b-dc6427644bde",
            "status": "completed",
            "file_type": "pdf",
            "file_size": 183623,
            "processed_at": "2026-02-01T12:07:25.319492",
            "error_message": null,
            "metadata": {
              "extracted_at": "2026-02-01T12:07:25.319423",
              "created": "2026-01-17T22:48:59.140968",
              "modified": "2025-10-11T23:57:32.221820",
              "accessed": "2026-01-18T15:58:30.866377",
              "page_count": null,
              "pdf_version": null
            }
          }
        ],
        "started_at": "2026-02-01T12:07:25.319499",
        "completed_at": "2026-02-01T12:07:25.319496"
      }
    ]
  }
}